PyEpiDAG-2.2.0.dist-info/METADATA
PyEpiDAG-2.2.0.dist-info/RECORD
PyEpiDAG-2.2.0.dist-info/WHEEL
PyEpiDAG-2.2.0.dist-info/top_level.txt
epidag/__init__.py
epidag/fn.py
epidag/util.py
epidag/bayesnet/__init__.py
epidag/bayesnet/bn.py
epidag/bayesnet/dag.py
epidag/bayesnet/distribution.py
epidag/bayesnet/fn.py
epidag/bayesnet/gene.py
epidag/bayesnet/loci.py
epidag/causality/__init__.py
epidag/causality/fn.py
epidag/causality/mcausal.py
epidag/data/__init__.py
epidag/data/frame.py
epidag/data/static.py
epidag/data/timeseries.py
epidag/factory/__init__.py
epidag/factory/arguments.py
epidag/factory/manager.py
epidag/factory/util.py
epidag/factory/workshop.py
epidag/fitting/__init__.py
epidag/fitting/bayesmodel.py
epidag/fitting/databm.py
epidag/fitting/fn.py
epidag/fitting/simubm.py
epidag/fitting/alg/__init__.py
epidag/fitting/alg/abc.py
epidag/fitting/alg/abcsmc.py
epidag/fitting/alg/fitter.py
epidag/fitting/alg/mcmc.py
epidag/fitting/alg/sir.py
epidag/simulation/__init__.py
epidag/simulation/actor.py
epidag/simulation/fn.py
epidag/simulation/parcore.py
epidag/simulation/simucore.py
epidag/simulation/simugroup.py
tests/__init__.py
tests/test_factory.py
tests/test_heirarchy.py
tests/test_loci.py
tests/test_parser.py
tests/test_pc_clone.py
