Metadata-Version: 2.1
Name: PyEpiDAG
Version: 2.2.0
Summary: Epidemiological inference with DAG
Home-page: https://github.com/TimeWz667/PyEpiDAG
Author: TimeWz
Author-email: TimeWz667@gmail.com
License: MIT
Platform: UNKNOWN
Requires-Dist: pandas
Requires-Dist: networkx
Requires-Dist: astunparse
Requires-Dist: numpy
Requires-Dist: scipy
Requires-Dist: matplotlib
